RASW/__init__.py
RASW/cli.py
RASW/example.py
RASW/FK/2D_4_link_arm.py
RASW/FK/__init__.py
RASW/FK/forward_kinematics.py
RASW/FK/Old/2D_4_link_arm backup.py
RASW/IK/2D_3_link_arm.py
RASW/IK/__init__.py
RASW/IK/inverse_kinematics.py
RASW/IK/Old/2D IKarm.py
RASW/IK/Old/2D_robotic_arm.py
rasw-1.0.0.dist-info/METADATA
rasw-1.0.0.dist-info/WHEEL
rasw-1.0.0.dist-info/entry_points.txt
rasw-1.0.0.dist-info/licenses/LICENSE
rasw-1.0.0.dist-info/RECORD
