Metadata-Version: 2.4
Name: RASW
Version: 1.0.0
Summary: A small robotic arm software package :)
Project-URL: Homepage, https://github.com/Jasminestrone/RASW
Project-URL: Documentation, https://github.com/Jasminestrone/RASW
Project-URL: Issues, https://google.com
Author-email: "Jazz, Nico, Patrick , Lloyd" <prt271828@example.com>
License-Expression: GPL-3.0-only
License-File: LICENSE
Classifier: Operating System :: OS Independent
Classifier: Programming Language :: Python :: 3
Requires-Python: >=3.8
Requires-Dist: matplotlib
Requires-Dist: numpy
